AUTHORS.rst
LICENSE
MANIFEST.in
README.rst
requirements.txt
setup.py
bigtempo/__init__.py
bigtempo/auditor.py
bigtempo/core.py
bigtempo/defaults.py
bigtempo/tagselection.py
bigtempo/utils.py
bigtempo.egg-info/PKG-INFO
bigtempo.egg-info/SOURCES.txt
bigtempo.egg-info/dependency_links.txt
bigtempo.egg-info/not-zip-safe
bigtempo.egg-info/requires.txt
bigtempo.egg-info/top_level.txt
bigtempo/processors/__init__.py
bigtempo/processors/dataframe_task.py
bigtempo/processors/simple_task.py