Metadata-Version: 1.1
Name: bigtempo
Version: 0.38.7
Summary: BigTempo is a powerful and scalable programming model, originally crafted for temporal data processment / analysis.
Home-page: https://github.com/rhlobo/bigtempo
Author: Roberto Haddock Lobo
Author-email: rhlobo+bigtempo@gmail.com
License: The MIT License (MIT)
